[
    {
        "name": "Kira",
        "contact": "36563697151",
        "website": "back.com",
        "websiteLike": "djd.com",
        "email": "kira@gmail.com",
        "message": "This test message.",
        "package": ""
    },
    {
        "name": "Alex",
        "contact": "16235421713",
        "website": "current.com",
        "websiteLike": "like.com",
        "email": "alex@gmail.com",
        "message": "This is test message.",
        "package": "BUGS REMOVING "
    },
    {
        "name": "Alex",
        "contact": "16235421713",
        "website": "current.com",
        "websiteLike": "like.com",
        "email": "alex@gmail.com",
        "message": "This is test message.",
        "package": "Inspiration"
    },
    {
        "name": "waqar",
        "contact": "03456521412",
        "website": "waqar.com",
        "websiteLike": "wsdf",
        "email": "waqar@gami.com",
        "message": "dfjdkfjkdj",
        "package": "Web Development"
    },
    {
        "name": "Wixe Arie",
        "contact": "12344567895",
        "website": "ffgsf.vom",
        "websiteLike": "test",
        "email": "waqar.net.pk@gmail.com",
        "message": "This is this message",
        "package": "BUGS REMOVING "
    }
]